[
  {
    "type": "impl",
    "name": "Distributor",
    "interface_name": "distributor::contract::IDistributor"
  },
  {
    "type": "struct",
    "name": "core::array::Span::<core::felt252>",
    "members": [
      {
        "name": "snapshot",
        "type": "@core::array::Array::<core::felt252>"
      }
    ]
  },
  {
    "type": "interface",
    "name": "distributor::contract::IDistributor",
    "items": [
      {
        "type": "function",
        "name": "claim",
        "inputs": [
          {
            "name": "amount",
            "type": "core::integer::u128"
          },
          {
            "name": "proof",
            "type": "core::array::Span::<core::felt252>"
          }
        ],
        "outputs": [],
        "state_mutability": "external"
      },
      {
        "type": "function",
        "name": "add_root",
        "inputs": [
          {
            "name": "new_root",
            "type": "core::felt252"
          }
        ],
        "outputs": [],
        "state_mutability": "external"
      },
      {
        "type": "function",
        "name": "get_root_for",
        "inputs": [
          {
            "name": "claimee",
            "type": "core::starknet::contract_address::ContractAddress"
          },
          {
            "name": "amount",
            "type": "core::integer::u128"
          },
          {
            "name": "proof",
            "type": "core::array::Span::<core::felt252>"
          }
        ],
        "outputs": [
          {
            "type": "core::felt252"
          }
        ],
        "state_mutability": "view"
      },
      {
        "type": "function",
        "name": "amount_already_claimed",
        "inputs": [
          {
            "name": "claimee",
            "type": "core::starknet::contract_address::ContractAddress"
          }
        ],
        "outputs": [
          {
            "type": "core::integer::u128"
          }
        ],
        "state_mutability": "view"
      },
      {
        "type": "function",
        "name": "roots",
        "inputs": [],
        "outputs": [
          {
            "type": "core::array::Span::<core::felt252>"
          }
        ],
        "state_mutability": "view"
      }
    ]
  },
  {
    "type": "constructor",
    "name": "constructor",
    "inputs": [
      {
        "name": "owner",
        "type": "core::starknet::contract_address::ContractAddress"
      }
    ]
  },
  {
    "type": "event",
    "name": "distributor::contract::Distributor::Claimed",
    "kind": "struct",
    "members": [
      {
        "name": "claimee",
        "type": "core::starknet::contract_address::ContractAddress",
        "kind": "data"
      },
      {
        "name": "amount",
        "type": "core::integer::u128",
        "kind": "data"
      }
    ]
  },
  {
    "type": "event",
    "name": "openzeppelin::access::ownable::ownable::OwnableComponent::OwnershipTransferred",
    "kind": "struct",
    "members": [
      {
        "name": "previous_owner",
        "type": "core::starknet::contract_address::ContractAddress",
        "kind": "key"
      },
      {
        "name": "new_owner",
        "type": "core::starknet::contract_address::ContractAddress",
        "kind": "key"
      }
    ]
  },
  {
    "type": "event",
    "name": "openzeppelin::access::ownable::ownable::OwnableComponent::OwnershipTransferStarted",
    "kind": "struct",
    "members": [
      {
        "name": "previous_owner",
        "type": "core::starknet::contract_address::ContractAddress",
        "kind": "key"
      },
      {
        "name": "new_owner",
        "type": "core::starknet::contract_address::ContractAddress",
        "kind": "key"
      }
    ]
  },
  {
    "type": "event",
    "name": "openzeppelin::access::ownable::ownable::OwnableComponent::Event",
    "kind": "enum",
    "variants": [
      {
        "name": "OwnershipTransferred",
        "type": "openzeppelin::access::ownable::ownable::OwnableComponent::OwnershipTransferred",
        "kind": "nested"
      },
      {
        "name": "OwnershipTransferStarted",
        "type": "openzeppelin::access::ownable::ownable::OwnableComponent::OwnershipTransferStarted",
        "kind": "nested"
      }
    ]
  },
  {
    "type": "event",
    "name": "distributor::contract::Distributor::Event",
    "kind": "enum",
    "variants": [
      {
        "name": "Claimed",
        "type": "distributor::contract::Distributor::Claimed",
        "kind": "nested"
      },
      {
        "name": "OwnableEvent",
        "type": "openzeppelin::access::ownable::ownable::OwnableComponent::Event",
        "kind": "nested"
      }
    ]
  }
]